allconnect/README.rst
allconnect/allconnect/__init__.py
allconnect/pyproject.toml
allconnect/tests/__init__.py
allconnect/tests/test_allconnect.py
allconnect-0.1.0.dist-info/WHEEL
allconnect-0.1.0.dist-info/METADATA
allconnect-0.1.0.dist-info/RECORD
