Metadata-Version: 2.1
Name: allconnect
Version: 0.1.0
Summary: Este é um pacote Python que oferece integrações com várias plataformas de comunicação, incluindo Discord, Telegram e WhatsApp, com a promessa de incluir mais integrações no futuro. Com ele, você pode enviar e receber mensagens, bem como realizar outras operações relacionadas à comunicação, usando essas plataformas. Este pacote é atualizável e estará em constante evolução para fornecer suporte para as plataformas mais populares 
Author: darkslwlinc
Requires-Python: >=3.10.0,<3.11
Classifier: Programming Language :: Python :: 3
Classifier: Programming Language :: Python :: 3.10
Requires-Dist: Flask (>=2.2.0,<3.0.0)
Requires-Dist: numpy (>=1.22.2,<2.0.0)
Requires-Dist: replit (>=3.2.4,<4.0.0)
Requires-Dist: urllib3 (>=1.26.12,<2.0.0)
